deingest/__init__.py
deingest/cli.py
deingest/core.py
deingest/exceptions.py
deingest/utils.py
tests/__init__.py
tests/test_core.py
deingest-0.1.0.dist-info/LICENSE
deingest-0.1.0.dist-info/METADATA
deingest-0.1.0.dist-info/WHEEL
deingest-0.1.0.dist-info/entry_points.txt
deingest-0.1.0.dist-info/top_level.txt
deingest-0.1.0.dist-info/RECORD
